{
  "prueba_GhA.Tests.Test1" : {
    "statistic" : {
      "failed" : 0,
      "broken" : 0,
      "skipped" : 0,
      "passed" : 2,
      "unknown" : 0,
      "total" : 2
    },
    "items" : [ {
      "uid" : "392fddfe7350793b",
      "reportUrl" : "https://juancarlosTudela.github.io/GithubActions_dotNet/13//#testresult/392fddfe7350793b",
      "status" : "passed",
      "statusDetails" : "Test1",
      "time" : {
        "start" : 1646338305974,
        "stop" : 1646338308666,
        "duration" : 2692
      }
    }, {
      "uid" : "8b19c1cf148f182c",
      "reportUrl" : "https://juancarlosTudela.github.io/GithubActions_dotNet/13//#testresult/8b19c1cf148f182c",
      "status" : "passed",
      "statusDetails" : "Test1",
      "time" : {
        "start" : 1646330257752,
        "stop" : 1646330260534,
        "duration" : 2782
      }
    } ]
  }
}